pysep/__init__.py
pysep/declust.py
pysep/pysep.py
pysep/recsec.py
pysep/configs/template_config.yaml
pysep/configs/alvizuri_tape_2018/2006-10-09T013528_NORTH_KOREA.yaml
pysep/configs/alvizuri_tape_2018/event_list_alvizuri_tape_2018.txt
pysep/configs/denali_nodal/2019-02-25T182230_CANTWELL_NODAL.yaml
pysep/configs/denali_nodal/2019-02-25T182230_CANTWELL_NONNODAL.yaml
pysep/configs/misc_events/1988-02-15T181000_KERNVILLE_EXPLOSION.yaml
pysep/configs/misc_events/2015-10-18T051831_TAAN_FJORD_LANDSLIDE.yaml
pysep/configs/misc_events/2016-01-24T103037_INISKIN.yaml
pysep/configs/mtuq_workshop_2022/2009-04-07T201255_ANCHORAGE.yaml
pysep/configs/mtuq_workshop_2022/2014-08-25T161903_ICELAND.yaml
pysep/configs/mtuq_workshop_2022/2017-09-03T033001_NORTH_KOREA.yaml
pysep/configs/mtuq_workshop_2022/2020-04-04T015318_SOUTHERN_CALIFORNIA.yaml
pysep/configs/scec/2002-03-16T213324_SOUTHERN_CALIFORNIA.yaml
pysep/configs/scec/event_list_scec_simulations.txt
pysep/configs/tape_etal_2018/2012-04-11T092157_TAPE_2018.yaml
pysep/configs/tape_etal_2018/event_list_tape_etal_2018.txt
pysep/configs/test/check_rotate_12Z.yaml
pysep/configs/test/test_config_rotate_bug.yaml
pysep/configs/test/test_mass_download.yaml
pysep/configs/test/test_remove_data_gaps.yaml
pysep/configs/test/test_station_ids.yaml
pysep/tests/test_declust.py
pysep/tests/test_process.py
pysep/tests/test_pysep.py
pysep/tests/test_recsec.py
pysep/tests/test_utils.py
pysep/utils/__init__.py
pysep/utils/cap_sac.py
pysep/utils/curtail.py
pysep/utils/fetch.py
pysep/utils/fmt.py
pysep/utils/io.py
pysep/utils/llnl.py
pysep/utils/mt.py
pysep/utils/plot.py
pysep/utils/process.py
pysep_adjtomo-0.7.1.dist-info/licenses/LICENSE.txt
pysep_adjtomo-0.7.1.dist-info/METADATA
pysep_adjtomo-0.7.1.dist-info/WHEEL
pysep_adjtomo-0.7.1.dist-info/entry_points.txt
pysep_adjtomo-0.7.1.dist-info/top_level.txt
pysep_adjtomo-0.7.1.dist-info/RECORD
