Metadata-Version: 2.4
Name: pysep-adjtomo
Version: 0.7.1
Summary: Python Seismogram Extraction and Processing
Author: adjTomo Dev Team
Author-email: adjtomo@gmail.com
License: MIT License
Project-URL: homepage, https://github.com/adjtomo
Project-URL: documentation, https://pysep.readthedocs.io
Project-URL: repository, https://github.com/adjtomo/pysep
Requires-Python: >=3.8
License-File: LICENSE.txt
Requires-Dist: obspy
Requires-Dist: cartopy
Requires-Dist: pyyaml
Provides-Extra: dev
Requires-Dist: pytest; extra == "dev"
Requires-Dist: ipython; extra == "dev"
Requires-Dist: ipdb; extra == "dev"
Dynamic: license-file
